rdrobust/__init__.py
rdrobust/funs.py
rdrobust/rdbwselect.py
rdrobust/rdplot.py
rdrobust/rdrobust.py
rdrobust-1.3.0.dist-info/METADATA
rdrobust-1.3.0.dist-info/WHEEL
rdrobust-1.3.0.dist-info/top_level.txt
rdrobust-1.3.0.dist-info/RECORD
