Metadata-Version: 2.1
Name: rdrobust
Version: 1.3.0
Summary: Implements local polynomial Regression Discontinuity (RD) point estimators with robust bias-corrected confidence intervals and inference procedures.
Home-page: https://github.com/rdpackages/rdrobust
Author: Ricardo Masini
Author-email: rmasini@ucdavis.edu
Project-URL: Bug Tracker, https://github.com/rdpackages/rdrobust/issues
Classifier: Programming Language :: Python :: 3
Classifier: License :: OSI Approved :: MIT License
Classifier: Operating System :: OS Independent
Requires-Python: >=3.6
Requires-Dist: numpy
Requires-Dist: pandas>=2.0.0
Requires-Dist: scipy
Requires-Dist: scikit-learn>=1.2.0
Requires-Dist: plotnine>=0.13.6
Requires-Dist: matplotlib>=3.9.2
